altimeter/__init__.py
altimeter/aws/__init__.py
altimeter/aws/aws2n.py
altimeter/aws/log_events.py
altimeter/aws/resource_service_region_mapping.py
altimeter/aws/settings.py
altimeter/aws/auth/__init__.py
altimeter/aws/auth/accessor.py
altimeter/aws/auth/cache.py
altimeter/aws/auth/exceptions.py
altimeter/aws/auth/multi_hop_accessor.py
altimeter/aws/resource/__init__.py
altimeter/aws/resource/account.py
altimeter/aws/resource/resource_spec.py
altimeter/aws/resource/unscanned_account.py
altimeter/aws/resource/util.py
altimeter/aws/resource/acm/__init__.py
altimeter/aws/resource/acm/certificate.py
altimeter/aws/resource/awslambda/__init__.py
altimeter/aws/resource/awslambda/function.py
altimeter/aws/resource/cloudtrail/__init__.py
altimeter/aws/resource/cloudtrail/trail.py
altimeter/aws/resource/dynamodb/__init__.py
altimeter/aws/resource/dynamodb/dynamodb_table.py
altimeter/aws/resource/ec2/__init__.py
altimeter/aws/resource/ec2/flow_log.py
altimeter/aws/resource/ec2/image.py
altimeter/aws/resource/ec2/instance.py
altimeter/aws/resource/ec2/internet_gateway.py
altimeter/aws/resource/ec2/network_interface.py
altimeter/aws/resource/ec2/region.py
altimeter/aws/resource/ec2/route_table.py
altimeter/aws/resource/ec2/security_group.py
altimeter/aws/resource/ec2/snapshot.py
altimeter/aws/resource/ec2/subnet.py
altimeter/aws/resource/ec2/transit_gateway.py
altimeter/aws/resource/ec2/transit_gateway_vpc_attachment.py
altimeter/aws/resource/ec2/volume.py
altimeter/aws/resource/ec2/vpc.py
altimeter/aws/resource/ec2/vpc_endpoint.py
altimeter/aws/resource/ec2/vpc_endpoint_service.py
altimeter/aws/resource/ec2/vpc_peering_connection.py
altimeter/aws/resource/eks/__init__.py
altimeter/aws/resource/eks/cluster.py
altimeter/aws/resource/elbv1/__init__.py
altimeter/aws/resource/elbv1/load_balancer.py
altimeter/aws/resource/elbv2/__init__.py
altimeter/aws/resource/elbv2/load_balancer.py
altimeter/aws/resource/elbv2/target_group.py
altimeter/aws/resource/events/__init__.py
altimeter-6.4.25.dist-info/LICENSE
altimeter-6.4.25.dist-info/METADATA
altimeter-6.4.25.dist-info/WHEEL
altimeter-6.4.25.dist-info/top_level.txt
altimeter-6.4.25.dist-info/RECORD
