Metadata-Version: 2.1
Name: altimeter
Version: 6.4.25
Summary: Graph AWS resources in Neptune
Home-page: https://github.com/tableau/altimeter
Author: Tableau
License: UNKNOWN
Platform: UNKNOWN
Classifier: Programming Language :: Python :: 3
Classifier: License :: OSI Approved :: MIT License
Classifier: Operating System :: OS Independent
Requires-Python: >=3.8,<3.10
License-File: LICENSE
Requires-Dist: MarkupSafe ==2.1.1
Requires-Dist: aws-requests-auth ==0.4.3
Requires-Dist: rdflib ==6.0.2
Requires-Dist: structlog ==20.2.0
Requires-Dist: boto3 ==1.28.80
Requires-Dist: jinja2 ==3.0.3
Requires-Dist: pydantic ==1.9.0
Requires-Dist: toml ==0.10.2
Requires-Dist: gremlinpython ==3.4.12
Requires-Dist: requests ==2.31.0
Requires-Dist: certifi ==2023.7.22
Requires-Dist: urllib3 ==1.26.18
Provides-Extra: qj
Requires-Dist: MarkupSafe ==2.1.1 ; extra == 'qj'
Requires-Dist: alembic ==1.4.2 ; extra == 'qj'
Requires-Dist: boto3 ==1.28.80 ; extra == 'qj'
Requires-Dist: fastapi ==0.96.0 ; extra == 'qj'
Requires-Dist: psycopg2-binary ==2.9.2 ; extra == 'qj'
Requires-Dist: sqlalchemy ==1.3.24 ; extra == 'qj'
Requires-Dist: tableauhyperapi ==0.0.18161 ; extra == 'qj'
Requires-Dist: tableauserverclient ==0.17.0 ; extra == 'qj'
Requires-Dist: uvicorn ==0.16.0 ; extra == 'qj'
Requires-Dist: urllib3 ==1.26.18 ; extra == 'qj'
